cal/__init__.py
cal/cal.py
shahmeer-1.0.dist-info/METADATA
shahmeer-1.0.dist-info/WHEEL
shahmeer-1.0.dist-info/top_level.txt
shahmeer-1.0.dist-info/RECORD
