Metadata-Version: 2.4
Name: Shahmeer
Version: 1.0
Summary: This is just a test package
Author: Shahmeer khan
Author-email: khanshahmeer200@gmail.com
Requires-Python: >=3.6
Dynamic: author
Dynamic: author-email
Dynamic: requires-python
Dynamic: summary
